tefy/__init__.py
tefy/tefy.py
tefy-0.1.4.dist-info/LICENSE
tefy-0.1.4.dist-info/WHEEL
tefy-0.1.4.dist-info/METADATA
tefy-0.1.4.dist-info/RECORD
