Metadata-Version: 2.1
Name: tefy
Version: 0.1.4
Summary: A very basic wrapper for conversions from doc, docx and odt to TEI XML
Home-page: https://github.com/03b8/tefy
License: MIT
Keywords: conversion,tei-xml,doc,docx,odt,markup
Author: Theo Costea
Author-email: theo.costea@gmail.com
Requires-Python: >=3.6,<4.0
Classifier: Intended Audience :: Developers
Classifier: Intended Audience :: Science/Research
Classifier: License :: OSI Approved :: MIT License
Classifier: Programming Language :: Python :: 3
Classifier: Programming Language :: Python :: 3.6
Classifier: Programming Language :: Python :: 3.7
Classifier: Topic :: Text Processing :: Markup :: XML
Requires-Dist: lxml (>=4.2.4,<5.0.0)
Requires-Dist: requests (>=2.22,<3.0)
Project-URL: Repository, https://github.com/03b8/tefy
